u_calc/__init__.py
u_calc/create_from_file.py
u_calc/measurement.py
u_calc-0.0.3.dist-info/LICENSE
u_calc-0.0.3.dist-info/METADATA
u_calc-0.0.3.dist-info/WHEEL
u_calc-0.0.3.dist-info/top_level.txt
u_calc-0.0.3.dist-info/RECORD
