Metadata-Version: 2.1
Name: u-calc
Version: 0.0.3
Summary: Calculator with uncertainties
Home-page: https://github.com/vini-fda/u-calc
Author: vini-fda, pekpuglia
Author-email: 
License: GPLv3
Platform: UNKNOWN
Classifier: Topic :: Scientific/Engineering :: Physics
Classifier: Programming Language :: Python :: 3
Classifier: License :: OSI Approved :: GNU General Public License v3 (GPLv3)
Classifier: Operating System :: OS Independent
Requires-Python: >=3.6
